north_admin/__init__.py
north_admin/admin_router.py
north_admin/app.py
north_admin/auth_provider.py
north_admin/crud.py
north_admin/dto.py
north_admin/exceptions.py
north_admin/filters.py
north_admin/helpers.py
north_admin/types.py
north_admin-0.1.4.dist-info/LICENSE
north_admin-0.1.4.dist-info/METADATA
north_admin-0.1.4.dist-info/WHEEL
north_admin-0.1.4.dist-info/RECORD
