Metadata-Version: 2.1
Name: north_admin
Version: 0.1.4
Summary: Easy-to-setup PWA Admin Panel solution based on FastAPI, async SQLAlchemy and pre-render Swelte UI
License: GNU GENERAL PUBLIC LICENSE
Author: Anton Nikolskiy
Author-email: a.nikolskiy@tyver.io
Requires-Python: >=3.11
Classifier: License :: Other/Proprietary License
Classifier: Programming Language :: Python :: 3
Classifier: Programming Language :: Python :: 3.11
Classifier: Programming Language :: Python :: 3.12
Requires-Dist: fastapi (>=0.104.1,<0.105.0)
Requires-Dist: greenlet (>=3.0.1,<4.0.0)
Requires-Dist: loguru (>=0.7.2,<0.8.0)
Requires-Dist: pyjwt (>=2.8.0,<3.0.0)
Requires-Dist: python-multipart (>=0.0.6,<0.0.7)
Requires-Dist: random-unicode-emoji (>=2.8,<3.0)
Requires-Dist: ruff (>=0.1.5,<0.2.0)
Requires-Dist: sqlalchemy (>=2.0.23,<3.0.0)
